pydl/dlutil.py
pydl_dl-0.1.dev0.dist-info/METADATA
pydl_dl-0.1.dev0.dist-info/RECORD
pydl_dl-0.1.dev0.dist-info/WHEEL
pydl_dl-0.1.dev0.dist-info/entry_points.txt
pydl_dl-0.1.dev0.dist-info/top_level.txt
