Metadata-Version: 2.1
Name: pydl-dl
Version: 0.1.dev0
Summary: A Library to download music from Youtube , Soundcloud and many others sites
Home-page: https://github.com/ayanbag/pydl
Author: Ayan Bag
Author-email: ayanbag9474@gmail.com
License: MIT
Platform: UNKNOWN
Classifier: Programming Language :: Python :: 3.5
Classifier: License :: OSI Approved :: MIT License
Requires-Python: >=3.4
Requires-Dist: requests
Requires-Dist: youtube-dl
